lakecoin/__init__.py
lakecoin/client.py
lakecoin/exceptions.py
lakecoin-0.1.0.dist-info/licenses/LICENSE
lakecoin-0.1.0.dist-info/METADATA
lakecoin-0.1.0.dist-info/WHEEL
lakecoin-0.1.0.dist-info/top_level.txt
lakecoin-0.1.0.dist-info/RECORD
