Metadata-Version: 2.4
Name: lakecoin
Version: 0.1.0
Summary: Простая и удобная Python-библиотека для работы с API мерчантов LakeCoin.
Author: The LakeCoin Team
License: MIT License
Project-URL: Homepage, https://lakecoin.ru
Project-URL: Documentation, https://lakecoin.ru/api-docs
Classifier: Programming Language :: Python :: 3
Classifier: License :: OSI Approved :: MIT License
Classifier: Operating System :: OS Independent
Classifier: Intended Audience :: Developers
Classifier: Topic :: Software Development :: Libraries :: Python Modules
Classifier: Topic :: Office/Business :: Financial
Requires-Python: >=3.7
License-File: LICENSE
Requires-Dist: requests>=2.25.0
Dynamic: license-file
